optax_shampoo/__init__.py
optax_shampoo/distributed_shampoo.py
optax_shampoo/distributed_shampoo_test.py
optax_shampoo/quantization_utils.py
optax_shampoo-0.0.5.dist-info/LICENSE
optax_shampoo-0.0.5.dist-info/METADATA
optax_shampoo-0.0.5.dist-info/WHEEL
optax_shampoo-0.0.5.dist-info/top_level.txt
optax_shampoo-0.0.5.dist-info/RECORD
