Metadata-Version: 2.1
Name: optax-shampoo
Version: 0.0.5
Summary: Shampoo (Second order Optimizer for Deep Learning) Optax Optimizer
Home-page: https://github.com/google-research/google-research/tree/master/scalable_shampoo
Author: rohananil
Author-email: rohan.anil@gmail.com
License: Apache Software License
Keywords: optax shampoo
Platform: UNKNOWN
Classifier: Programming Language :: Python :: 3
Classifier: License :: OSI Approved :: Apache Software License
Classifier: Operating System :: OS Independent
Classifier: Development Status :: 3 - Alpha
Requires-Python: >=3.6
License-File: LICENSE
